modo/__init__.py
modo/app.py
modo_todo-0.1.0.dist-info/METADATA
modo_todo-0.1.0.dist-info/WHEEL
modo_todo-0.1.0.dist-info/entry_points.txt
modo_todo-0.1.0.dist-info/RECORD
