Metadata-Version: 2.1
Name: modo-todo
Version: 0.1.0
Summary: todos and more from simple markdown
Author-Email: James Turk <dev@jpt.sh>
License: MIT
Requires-Python: >=3.12
Requires-Dist: click>=8.1.7
Requires-Dist: rich>=13.7.1
Requires-Dist: python-dateutil>=2.9.0.post0
